autora/theorist/rnn_sindy_rl/__init__.py
autora/theorist/rnn_sindy_rl/basic_test.py
autora/theorist/rnn_sindy_rl/rnn_main.py
autora/theorist/rnn_sindy_rl/sindy_main.py
autora/theorist/rnn_sindy_rl/data/bahrami_100.csv
autora/theorist/rnn_sindy_rl/data/dataset_train.pkl
autora/theorist/rnn_sindy_rl/data/sindy_data.csv
autora/theorist/rnn_sindy_rl/params/params_rnn_b3.pkl
autora/theorist/rnn_sindy_rl/resources/bandits.py
autora/theorist/rnn_sindy_rl/resources/plotting.py
autora/theorist/rnn_sindy_rl/resources/rnn.py
autora/theorist/rnn_sindy_rl/resources/rnn_training.py
autora/theorist/rnn_sindy_rl/resources/rnn_utils.py
autora/theorist/rnn_sindy_rl/resources/sindy_training.py
autora/theorist/rnn_sindy_rl/resources/sindy_utils.py
autora/theorist/rnn_sindy_rl/utils/dataset_to_list.py
rnn_sindy_rl-0.0.1a0.dist-info/LICENSE
rnn_sindy_rl-0.0.1a0.dist-info/METADATA
rnn_sindy_rl-0.0.1a0.dist-info/WHEEL
rnn_sindy_rl-0.0.1a0.dist-info/top_level.txt
rnn_sindy_rl-0.0.1a0.dist-info/RECORD
