Metadata-Version: 2.1
Name: rnn_sindy_rl
Version: 0.0.1a0
Summary: An AutoRA theorist for discovering reinforcement learning models from behavioral experiments.
Author-email: Sebastian Musslick <sebastian@musslick.de>
License: Copyright (c) 2024 Sebastian Musslick
Project-URL: homepage, http://www.empiricalresearch.ai
Project-URL: repository, https://github.com/AutoResearch/rnn-sindy-rl.git
Project-URL: documentation, https://autoresearch.github.io/autora/
Requires-Python: <4,>=3.8
License-File: LICENSE
Requires-Dist: autora-core
Requires-Dist: scikit-learn
Requires-Dist: pysindy
Requires-Dist: torch
Requires-Dist: typeguard
Provides-Extra: dev
Requires-Dist: autora-core[dev] ; extra == 'dev'
